steam_shortcuts_cli/__init__.py
steam_shortcuts_cli/cli.py
steam_shortcuts_cli/crc.py
steam_shortcuts_cli/manager.py
steam_shortcuts_cli/models.py
steam_shortcuts_cli/vdf.py
steam_shortcuts_cli-0.3.0.dist-info/METADATA
steam_shortcuts_cli-0.3.0.dist-info/WHEEL
steam_shortcuts_cli-0.3.0.dist-info/entry_points.txt
steam_shortcuts_cli-0.3.0.dist-info/licenses/LICENSE
steam_shortcuts_cli-0.3.0.dist-info/RECORD
