Metadata-Version: 2.4
Name: steam-shortcuts-cli
Version: 0.3.0
Summary: A simple cli to manage steam external shortcuts
Project-URL: Homepage, https://github.com/lava/steam-shortcuts-cli
Project-URL: Repository, https://github.com/lava/steam-shortcuts-cli
Project-URL: Issues, https://github.com/lava/steam-shortcuts-cli/issues
Author: Benno Evers
License-Expression: MIT
License-File: LICENSE
Classifier: Development Status :: 3 - Alpha
Classifier: Environment :: Console
Classifier: License :: OSI Approved :: MIT License
Classifier: Operating System :: OS Independent
Classifier: Programming Language :: Python :: 3
Classifier: Topic :: Games/Entertainment
Requires-Python: >=3.14
Requires-Dist: docopt
Requires-Dist: pillow>=10.0
Requires-Dist: pydantic>=2.0
